SMOPCA/__init__.py
SMOPCA/model.py
SMOPCA/utils.py
SMOPCA-0.1.1.dist-info/LICENSE
SMOPCA-0.1.1.dist-info/METADATA
SMOPCA-0.1.1.dist-info/WHEEL
SMOPCA-0.1.1.dist-info/top_level.txt
SMOPCA-0.1.1.dist-info/RECORD
