Metadata-Version: 2.1
Name: SMOPCA
Version: 0.1.1
Summary: A novel spatially aware multi-omics dimension reduction method
Home-page: https://github.com/cmhimself/SMOPCA
Author: Mo Chen
Author-email: mochen@smail.nju.edu.cn
Classifier: Programming Language :: Python :: 3
Classifier: Programming Language :: Python :: 3.10
Classifier: License :: OSI Approved :: MIT License
Classifier: Operating System :: OS Independent
Requires-Python: >=3.10.0
License-File: LICENSE
Requires-Dist: anndata==0.8.0
Requires-Dist: h5py==3.8.0
Requires-Dist: matplotlib==3.6.3
Requires-Dist: numpy==1.23.5
Requires-Dist: pandas==1.5.3
Requires-Dist: scanpy==1.9.1
Requires-Dist: scikit-learn==1.2.1
Requires-Dist: scipy==1.10.0
